bibletk/__init__.py
bibletk/_version.py
bibletk/bibletk.py
bibletk/book_names.txt
bibletk/hb5.txt
bibletk-0.2.dist-info/DESCRIPTION.rst
bibletk-0.2.dist-info/entry_points.txt
bibletk-0.2.dist-info/METADATA
bibletk-0.2.dist-info/metadata.json
bibletk-0.2.dist-info/RECORD
bibletk-0.2.dist-info/top_level.txt
bibletk-0.2.dist-info/WHEEL
data/__init__.py
data/book_names.txt
data/hb5.txt
tests/__init__.py
tests/test_bibletk.py
