Metadata-Version: 2.0
Name: bibletk
Version: 0.2
Summary: Toolkit for bible
Home-page: https://github.com/jeroyang/bibletk
Author: Chia-Jung, Yang
Author-email: jeroyang@gmail.com
License: MIT
Keywords: bibletk
Platform: UNKNOWN
Classifier: Development Status :: 2 - Pre-Alpha
Classifier: Intended Audience :: Developers
Classifier: License :: OSI Approved :: BSD License
Classifier: Natural Language :: English
Classifier: Programming Language :: Python :: 2
Classifier: Programming Language :: Python :: 2.6
Classifier: Programming Language :: Python :: 2.7
Classifier: Programming Language :: Python :: 3
Classifier: Programming Language :: Python :: 3.3
Classifier: Programming Language :: Python :: 3.4
Requires-Dist: wheel (==0.23.0)
Requires-Dist: future (==0.15.2)
Requires-Dist: python-pptx (==0.5.8)
Requires-Dist: txttk (==0.3.4)
